README.md
setup.py
moderninput/__init__.py
moderninput/_base.py
moderninput/_input_bool.py
moderninput/_input_choice.py
moderninput/_input_dir.py
moderninput/_input_email.py
moderninput/_input_file.py
moderninput/_input_filedir.py
moderninput/_input_float.py
moderninput/_input_int.py
moderninput/_input_intfloat.py
moderninput/_input_ipv4.py
moderninput/_input_length.py
moderninput/_input_regex.py
moderninput/_typecheck.py
moderninput/_utils.py
moderninput/patterns.py
moderninput.egg-info/PKG-INFO
moderninput.egg-info/SOURCES.txt
moderninput.egg-info/dependency_links.txt
moderninput.egg-info/top_level.txt